{
  "mode": "formula",
  "timestamp_root": "2026-03-22_163414_formula",
  "data_dir": "C:\\Users\\mincu\\Desktop\\topological_gravity_project\\data\\processed\\sparc_normalized_beta_abar",
  "output_root": "C:\\Users\\mincu\\Desktop\\topological_gravity_project\\outputs\\galaxy_rotation\\pipeline_beta_formula\\2026-03-22_163414_formula",
  "n_files_found": 175,
  "n_ok": 175,
  "n_failed": 0,
  "parameters": {
    "beta_value": 200.0,
    "structural_mode": "sigma_over_r",
    "sigma_proxy_mode": "log_ratio",
    "sigma_damping_mode": "bar_over_obs",
    "sigma_positive_only": true,
    "D_bg": 0.0,
    "upsilon_disk": 1.0,
    "upsilon_bul": 1.0,
    "beta_min": 0.0,
    "beta_max": 2000.0,
    "beta_ridge": 1e-12,
    "use_nonnegative_target": false,
    "formula_p": 1.0737936939240849,
    "formula_q": 1.0737936939240849,
    "formula_lambda_beta": 3.1772138142832826,
    "formula_g_choice": "gbar_char_logmean",
    "formula_sigma_choice": "sigma_char_rms",
    "use_dimension_proxy": false,
    "formula_d_ref": 3.0,
    "formula_dim_sensitivity": 0.85,
    "formula_dim_g_power": 1.0,
    "formula_dim_sigma_power": 1.0,
    "formula_d_min": 1.5,
    "formula_d_max": 4.5,
    "formula_dim_boost_lambda": 0.85,
    "formula_dim_transition": 0.35,
    "formula_dim_boost_max": 2.5,
    "shared_g0": 561.0610296982485,
    "shared_sigma0": 0.5272732878135848,
    "sigma_weight_mode": "formula",
    "sigma_weight_value": 0.5,
    "sigma_weight_u": 0.5368968469620424,
    "sigma_weight_v": 0.5368968469620424,
    "sigma_weight_lambda": 1.782474071139124,
    "sigma_weight_g_choice": "gbar_char_logmean",
    "sigma_weight_sigma_choice": "sigma_char_rms",
    "use_estimated_params": true,
    "estimated_params_json": "outputs\\galaxy_rotation\\pipeline_beta_formula\\estimated_formula_params.json"
  },
  "summary_csv": "C:\\Users\\mincu\\Desktop\\topological_gravity_project\\outputs\\galaxy_rotation\\pipeline_beta_formula\\2026-03-22_163414_formula\\summaries\\rotation_pipeline_summary_formula.csv"
}